LICENSE
NOTICE.txt
landing-page.md
pyproject.toml
dash_bootstrap_components/Accordion.py
dash_bootstrap_components/AccordionItem.py
dash_bootstrap_components/Alert.py
dash_bootstrap_components/Badge.py
dash_bootstrap_components/Breadcrumb.py
dash_bootstrap_components/Button.py
dash_bootstrap_components/ButtonGroup.py
dash_bootstrap_components/Card.py
dash_bootstrap_components/CardBody.py
dash_bootstrap_components/CardFooter.py
dash_bootstrap_components/CardGroup.py
dash_bootstrap_components/CardHeader.py
dash_bootstrap_components/CardImg.py
dash_bootstrap_components/CardImgOverlay.py
dash_bootstrap_components/CardLink.py
dash_bootstrap_components/Carousel.py
dash_bootstrap_components/Checkbox.py
dash_bootstrap_components/Checklist.py
dash_bootstrap_components/Col.py
dash_bootstrap_components/Collapse.py
dash_bootstrap_components/Container.py
dash_bootstrap_components/DropdownMenu.py
dash_bootstrap_components/DropdownMenuItem.py
dash_bootstrap_components/Fade.py
dash_bootstrap_components/Form.py
dash_bootstrap_components/FormFeedback.py
dash_bootstrap_components/FormFloating.py
dash_bootstrap_components/FormText.py
dash_bootstrap_components/Input.py
dash_bootstrap_components/InputGroup.py
dash_bootstrap_components/InputGroupText.py
dash_bootstrap_components/Label.py
dash_bootstrap_components/ListGroup.py
dash_bootstrap_components/ListGroupItem.py
dash_bootstrap_components/Modal.py
dash_bootstrap_components/ModalBody.py
dash_bootstrap_components/ModalFooter.py
dash_bootstrap_components/ModalHeader.py
dash_bootstrap_components/ModalTitle.py
dash_bootstrap_components/Nav.py
dash_bootstrap_components/NavItem.py
dash_bootstrap_components/NavLink.py
dash_bootstrap_components/Navbar.py
dash_bootstrap_components/NavbarBrand.py
dash_bootstrap_components/NavbarSimple.py
dash_bootstrap_components/NavbarToggler.py
dash_bootstrap_components/Offcanvas.py
dash_bootstrap_components/Pagination.py
dash_bootstrap_components/Placeholder.py
dash_bootstrap_components/Popover.py
dash_bootstrap_components-1.7.0.dist-info/METADATA
dash_bootstrap_components-1.7.0.dist-info/WHEEL
dash_bootstrap_components-1.7.0.dist-info/licenses/LICENSE
dash_bootstrap_components-1.7.0.dist-info/licenses/NOTICE.txt
dash_bootstrap_components-1.7.0.dist-info/RECORD
