Metadata-Version: 2.4
Name: dash-bootstrap-components
Version: 1.7.0
Summary: Bootstrap themed components for use in Plotly Dash
Project-URL: Homepage, https://dash-bootstrap-components.opensource.faculty.ai/
Project-URL: Source, https://github.com/facultyai/dash-bootstrap-components/
Project-URL: Bug Reports, https://github.com/facultyai/dash-bootstrap-components/issues
Author: Faculty Science Ltd, Pascal Bugnion
Author-email: Tom Begley <tomcbegley@gmail.com>
Maintainer-email: Tom Begley <tomcbegley@gmail.com>
License:                               Apache License
License-File: LICENSE
License-File: NOTICE.txt
Classifier: Framework :: Dash
Classifier: License :: OSI Approved :: Apache Software License
Classifier: Programming Language :: Python :: 3.9
Classifier: Programming Language :: Python :: 3.10
Classifier: Programming Language :: Python :: 3.11
Classifier: Programming Language :: Python :: 3.12
Classifier: Programming Language :: Python :: 3.13
Requires-Python: <4,>=3.9
Requires-Dist: dash>=2.0.0
Provides-Extra: pandas
Requires-Dist: numpy>=2.0.2; extra == 'pandas'
Requires-Dist: pandas>=2.2.3; extra == 'pandas'
